xadmin_nimbus/__init__.py
xadmin_nimbus/admin.py
xadmin_nimbus/adminx.py
xadmin_nimbus/apps.py
xadmin_nimbus/models.py
xadmin_nimbus/tests.py
xadmin_nimbus/views.py
xadmin_nimbus/locale/en/LC_MESSAGES/django.mo
xadmin_nimbus/locale/en/LC_MESSAGES/django.po
xadmin_nimbus/locale/zh/LC_MESSAGES/django.mo
xadmin_nimbus/locale/zh/LC_MESSAGES/django.po
xadmin_nimbus/locale/zh-hans/LC_MESSAGES/django.mo
xadmin_nimbus/locale/zh-hans/LC_MESSAGES/django.po
xadmin_nimbus/migrations/__init__.py
xadmin_nimbus/static/xadmin/js/xadmin.echarts.common.min.js
xadmin_nimbus/static/xadmin/js/xadmin.echarts.min.js
xadmin_nimbus/static/xadmin/js/xadmin.echarts.simple.min.js
xadmin_nimbus/static/xadmin/js/xadmin.echarts.theme.dark.js
xadmin_nimbus/static/xadmin/js/xadmin.echarts.theme.infographic.js
xadmin_nimbus/static/xadmin/js/xadmin.echarts.theme.macarons.js
xadmin_nimbus/static/xadmin/js/xadmin.echarts.theme.roma.js
xadmin_nimbus/static/xadmin/js/xadmin.echarts.theme.shine.js
xadmin_nimbus/static/xadmin/js/xadmin.echarts.theme.vintage.js
xadmin_nimbus/static/xadmin/js/xadmin.jquery.flot.stack.js
xadmin_nimbus/static/xadmin/js/xadmin.plugin.echarts.js
xadmin_nimbus/static/xadmin/js/xadmin.plugin.widget.echarts.js
xadmin_nimbus/templates/xadmin/blocks/model_list.results_top.echarts.html
xadmin_nimbus/templates/xadmin/widgets/echarts.html
xadmin_nimbus/widgets/__init__.py
xadmin_nimbus/widgets/constants.py
xadmin_nimbus/widgets/echarts.py
xadmin_nimbus/widgets/flot.py
xadmin_nimbus/widgets/mixin.py
xadmin_nimbus-1.2.6.dist-info/DESCRIPTION.rst
xadmin_nimbus-1.2.6.dist-info/LICENSE.txt
xadmin_nimbus-1.2.6.dist-info/METADATA
xadmin_nimbus-1.2.6.dist-info/RECORD
xadmin_nimbus-1.2.6.dist-info/WHEEL
xadmin_nimbus-1.2.6.dist-info/metadata.json
xadmin_nimbus-1.2.6.dist-info/top_level.txt
